dreamutils/__init__.py
dreamutils/_internal.py
dreamutils/encoding.py
dreamutils/file.py
dreamutils/net.py
dreamutils/os.py
dreamutils/python.py
dreamutils/sort.py
dreamutils/types/__init__.py
dreamutils/types/dict.py
dreamutils/types/string.py
dreamutils/types/xml.py
dreamutils-0.1.1.dist-info/LICENCE
dreamutils-0.1.1.dist-info/METADATA
dreamutils-0.1.1.dist-info/WHEEL
dreamutils-0.1.1.dist-info/top_level.txt
dreamutils-0.1.1.dist-info/RECORD
