Metadata-Version: 2.1
Name: dreamutils
Version: 0.1.1
Summary: A collection of useful and often repeated python methods
Home-page: https://github.com/ByteDream/dreamutils
Author: ByteDream
Author-email: 
License: LGPL-3.0
Platform: UNKNOWN
Classifier: License :: OSI Approved :: GNU Lesser General Public License v3 (LGPLv3)
Classifier: Operating System :: OS Independent
Classifier: Development Status :: 4 - Beta
Classifier: Topic :: Software Development :: Libraries :: Python Modules
Classifier: Programming Language :: Python :: 3.6
Classifier: Programming Language :: Python :: 3.7
Classifier: Programming Language :: Python :: 3.8
Classifier: Programming Language :: Python :: 3.9
Requires-Python: >=3.6.*
